pyaudiotoolslib/__init__.py
pyaudiotoolslib/utils.cp312-win_amd64.pyd
pyaudiotoolslib/utils.pyi
pyaudiotoolslib/wavfile.cp312-win_amd64.pyd
pyaudiotoolslib/wavfile.pyi
pyaudiotoolslib-0.0.2.dist-info/METADATA
pyaudiotoolslib-0.0.2.dist-info/WHEEL
pyaudiotoolslib-0.0.2.dist-info/licenses/LICENSE
pyaudiotoolslib-0.0.2.dist-info/RECORD
